Metadata-Version: 2.4
Name: redis-mcp-server-adv
Version: 0.3.5
Summary: Redis MCP Server - Model Context Protocol server for Redis forked from https://github.com/yuchenhui/mcp-redis
Keywords: redis,mcp,model-context-protocol,ai,llm
Author: Marshall Yu
Author-email: Marshall Yu <iuhnehcuy@gmail.com>
License-Expression: MIT
Classifier: Development Status :: 4 - Beta
Classifier: Intended Audience :: Developers
Classifier: Programming Language :: Python :: 3
Classifier: Programming Language :: Python :: 3.10
Classifier: Programming Language :: Python :: 3.11
Classifier: Programming Language :: Python :: 3.12
Classifier: Programming Language :: Python :: 3.13
Classifier: Topic :: Database
Classifier: Topic :: Software Development :: Libraries :: Python Modules
Requires-Dist: mcp[cli]>=1.9.4
Requires-Dist: redis>=6.0.0
Requires-Dist: dotenv>=0.9.9
Requires-Dist: numpy>=2.2.4
Requires-Dist: click>=8.0.0
Requires-Python: >=3.10
Project-URL: Homepage, https://github.com/yuchenhui/mcp-redis
Project-URL: Issues, https://github.com/yuchenhui/mcp-redis/issues
Project-URL: Repository, https://github.com/yuchenhui/mcp-redis
